retro/VERSION
retro/__init__.py
retro/_retro.cpython-310-x86_64-linux-gnu.so
retro/enums.py
retro/rendering.py
retro/retro_env.py
retro/cores/fceumm.json
retro/cores/fceumm_libretro.so
retro/cores/gambatte.json
retro/cores/gambatte_libretro.so
retro/cores/genesis_plus_gx.json
retro/cores/genesis_plus_gx_libretro.so
retro/cores/mednafen_pce_fast.json
retro/cores/mednafen_pce_fast_libretro.so
retro/cores/mgba.json
retro/cores/mgba_libretro.so
retro/cores/picodrive.json
retro/cores/picodrive_libretro.so
retro/cores/snes9x.json
retro/cores/snes9x_libretro.so
retro/cores/stella.json
retro/cores/stella_libretro.so
retro/data/__init__.py
retro/data/stable/__init__.py
retro/data/stable/VirtuaFighter-32x/AkiraVsJacky.state
retro/data/stable/VirtuaFighter-32x/data.json
retro/data/stable/VirtuaFighter-32x/metadata.json
retro/data/stable/VirtuaFighter-32x/rom.sha
retro/data/stable/VirtuaFighter-32x/scenario.json
retro/examples/__init__.py
retro/examples/brute.py
retro/examples/determinism.py
retro/examples/discretizer.py
retro/examples/interactive.py
retro/examples/ppo.py
retro/examples/random_agent.py
retro/examples/retro_interactive.py
retro/examples/trivial_random_agent.py
retro/examples/trivial_random_agent_multiplayer.py
retro/import/__init__.py
retro/import/__main__.py
retro/import/sega_classics.py
retro/scripts/__init__.py
retro/scripts/import_path.py
retro/scripts/import_sega_classics.py
retro/scripts/playback_movie.py
stable_retro-0.0.1.dist-info/LICENSE
stable_retro-0.0.1.dist-info/LICENSES.md
stable_retro-0.0.1.dist-info/METADATA
stable_retro-0.0.1.dist-info/WHEEL
stable_retro-0.0.1.dist-info/top_level.txt
stable_retro-0.0.1.dist-info/RECORD
