Metadata-Version: 2.1
Name: stable-retro
Version: 0.0.1
Home-page: https://github.com/farama-foundation/stable-retro
Author: Farama Foundation
Author-email: contact@farama.org
License: MIT
Requires-Python: >=3.6.0,<3.11
License-File: LICENSE
License-File: LICENSES.md
Requires-Dist: gymnasium (>=0.27.1)
Requires-Dist: pyglet (==1.*,>=1.3.2)
